[{"model": "core.color", "pk": 3, "fields": {"name": "d9b2ae"}}, {"model": "core.color", "pk": 4, "fields": {"name": "5dabba"}}, {"model": "core.color", "pk": 5, "fields": {"name": "1b1c2f"}}, {"model": "core.color", "pk": 6, "fields": {"name": "167b9e"}}, {"model": "core.color", "pk": 7, "fields": {"name": "910505"}}, {"model": "core.color", "pk": 8, "fields": {"name": "e1a307"}}, {"model": "core.color", "pk": 9, "fields": {"name": "349273"}}, {"model": "core.color", "pk": 10, "fields": {"name": "053c71"}}, {"model": "core.color", "pk": 11, "fields": {"name": "a46c74"}}, {"model": "core.color", "pk": 12, "fields": {"name": "1d85ad"}}]